tl/__init__.py
tl/exp.py
tl_kec-0.0.0.dist-info/METADATA
tl_kec-0.0.0.dist-info/WHEEL
tl_kec-0.0.0.dist-info/top_level.txt
tl_kec-0.0.0.dist-info/RECORD
